fannypack/__init__.py
fannypack/py.typed
fannypack/data/__init__.py
fannypack/data/_drive_files.py
fannypack/data/_trajectories_file.py
fannypack/nn/__init__.py
fannypack/nn/resblocks.py
fannypack/scripts/__init__.py
fannypack/scripts/buddy_cli.py
fannypack/scripts/_buddy_cli_include/__init__.py
fannypack/scripts/_buddy_cli_include/_subcommand.py
fannypack/scripts/_buddy_cli_include/_subcommand_delete.py
fannypack/scripts/_buddy_cli_include/_subcommand_info.py
fannypack/scripts/_buddy_cli_include/_subcommand_list.py
fannypack/scripts/_buddy_cli_include/_subcommand_rename.py
fannypack/scripts/_buddy_cli_include/_utils.py
fannypack/utils/__init__.py
fannypack/utils/_buddy.py
fannypack/utils/_conversions.py
fannypack/utils/_deprecation.py
fannypack/utils/_git.py
fannypack/utils/_math.py
fannypack/utils/_module_freezing.py
fannypack/utils/_pdb_safety_net.py
fannypack/utils/_slice_wrapper.py
fannypack/utils/_squeeze.py
fannypack/utils/_stopwatch.py
fannypack/utils/_buddy_include/__init__.py
fannypack/utils/_buddy_include/_checkpointing.py
fannypack/utils/_buddy_include/_logging.py
fannypack/utils/_buddy_include/_metadata.py
fannypack/utils/_buddy_include/_optimizer.py
tests/__init__.py
tests/fixtures.py
tests/utils/__init__.py
tests/utils/test_buddy_checkpointing.py
tests/utils/test_buddy_metadata.py
tests/utils/test_buddy_training.py
tests/utils/test_conversions.py
tests/utils/test_git.py
tests/utils/test_math.py
tests/utils/test_module_freezing.py
tests/utils/test_pdb_safety_net.py
tests/utils/test_slice_wrapper.py
tests/utils/test_squeeze.py
tests/utils/test_stopwatch.py
fannypack-0.0.25.dist-info/LICENSE
fannypack-0.0.25.dist-info/METADATA
fannypack-0.0.25.dist-info/WHEEL
fannypack-0.0.25.dist-info/entry_points.txt
fannypack-0.0.25.dist-info/top_level.txt
fannypack-0.0.25.dist-info/RECORD
