Metadata-Version: 2.1
Name: fannypack
Version: 0.0.25
Summary: PyTorch utilities
Home-page: http://github.com/brentyi/fannypack
Author: brentyi
Author-email: brentyi@berkeley.edu
License: MIT
Platform: UNKNOWN
Classifier: Programming Language :: Python :: 3.6
Classifier: Programming Language :: Python :: 3.7
Classifier: Programming Language :: Python :: 3.8
Classifier: License :: OSI Approved :: MIT License
Classifier: Operating System :: OS Independent
Requires-Python: >=3.6
License-File: LICENSE
Requires-Dist: argcomplete
Requires-Dist: beautifultable (>=1.0.0)
Requires-Dist: dill
Requires-Dist: h5py
Requires-Dist: numpy
Requires-Dist: pygments
Requires-Dist: pyyaml
Requires-Dist: simple-term-menu
Requires-Dist: tensorboard
Requires-Dist: termcolor
Requires-Dist: torch
Requires-Dist: tqdm
Requires-Dist: Pillow
